mbo_suite3d-0.0.7.dist-info/licenses/LICENSE
suite3d/__init__.py
suite3d/__main__.py
suite3d/corrmap.py
suite3d/curation.py
suite3d/dcnv.py
suite3d/default_params.py
suite3d/detection3d.py
suite3d/developer.py
suite3d/extension.py
suite3d/file_utils.py
suite3d/init_pass.py
suite3d/iter_step.py
suite3d/job.py
suite3d/labeller.py
suite3d/lbmio.py
suite3d/nbtools.py
suite3d/plot_utils.py
suite3d/quality_metrics.py
suite3d/reference_image.py
suite3d/reg_3d.py
suite3d/register_gpu.py
suite3d/s2p_registration.py
suite3d/svd_utils.py
suite3d/ui.py
suite3d/utils.py
suite3d/io/__init__.py
suite3d/io/deprecated_file_utils.py
suite3d/io/deprecated_tiff_utils.py
suite3d/io/lbmio.py
suite3d/io/s3dio.py
suite3d/io/tiff_utils.py
mbo_suite3d-0.0.7.dist-info/METADATA
mbo_suite3d-0.0.7.dist-info/WHEEL
mbo_suite3d-0.0.7.dist-info/entry_points.txt
mbo_suite3d-0.0.7.dist-info/top_level.txt
mbo_suite3d-0.0.7.dist-info/RECORD
