Metadata-Version: 2.4
Name: mbo_suite3d
Version: 0.0.7
Summary: Fast, volumetric cell detection. In development.
License: AGPL-3.0-or-later
Project-URL: homepage, https://github.com/alihaydaroglu/suite3d
Keywords: Pipeline,Numpy,Microscopy,ScanImage,Suite2p,Volumetric
Requires-Python: <3.13,>=3.11
License-File: LICENSE
Requires-Dist: dask>=2025.3.0
Requires-Dist: tifffile>=2021.3.4
Requires-Dist: zarr>=2.18.3
Requires-Dist: matplotlib>=3.10.1
Requires-Dist: torch>=1.7.1
Requires-Dist: natsort
Requires-Dist: rastermap>0.1.0
Requires-Dist: scanimage-tiff-reader>=1.4.1
Requires-Dist: importlib-metadata
Requires-Dist: paramiko
Requires-Dist: pynwb
Requires-Dist: sbxreader
Requires-Dist: imreg-dft-nw
Requires-Dist: click
Requires-Dist: ipython
Requires-Dist: jupyterlab==4.2.6
Requires-Dist: jupyter_rfb
Requires-Dist: pyqt5==5.15.11
Requires-Dist: pyqtgraph
Requires-Dist: ipykernel
Requires-Dist: napari
Requires-Dist: scikit-image
Requires-Dist: dask-image
Requires-Dist: pyqt5-qt5==5.15.2; sys_platform == "win32"
Requires-Dist: pyqt5-qt5==5.15.16; sys_platform == "darwin" or sys_platform == "linux"
Provides-Extra: gpu
Provides-Extra: mrc
Requires-Dist: mrcfile; extra == "mrc"
Provides-Extra: fpl
Requires-Dist: fastplotlib; extra == "fpl"
Requires-Dist: ipykernel; extra == "fpl"
Requires-Dist: jupyter_rfb; extra == "fpl"
Requires-Dist: imgui-bundle; extra == "fpl"
Provides-Extra: all
Requires-Dist: fastplotlib; extra == "all"
Requires-Dist: ipykernel; extra == "all"
Requires-Dist: jupyter_rfb; extra == "all"
Requires-Dist: imgui-bundle; extra == "all"
Requires-Dist: mrcfile; extra == "all"
Dynamic: license-file
